mayapy_launcher/__init__.py
mayapy_launcher-0.1.0.dist-info/entry_points.txt
mayapy_launcher-0.1.0.dist-info/LICENSE
mayapy_launcher-0.1.0.dist-info/WHEEL
mayapy_launcher-0.1.0.dist-info/METADATA
mayapy_launcher-0.1.0.dist-info/RECORD
