Metadata-Version: 2.1
Name: mayapy-launcher
Version: 0.1.0
Summary: Easily launch any version of mayapy
License: MIT
Author: Loïc Pinsard
Author-email: muream@gmail.com
Requires-Python: >=3.7,<4.0
Classifier: License :: OSI Approved :: MIT License
Classifier: Programming Language :: Python :: 3
Classifier: Programming Language :: Python :: 3.10
Classifier: Programming Language :: Python :: 3.7
Classifier: Programming Language :: Python :: 3.8
Classifier: Programming Language :: Python :: 3.9
Requires-Dist: click (>=8.1.3,<9.0.0)
